.DS_Store
stairs/__init__.py
stairs/conf.py
stairs/errors.py
stairs/session.py
stairs/settings.py
stairs/states.py
stairs/transaction.py
stairs-0.0.1b3.dist-info/METADATA
stairs-0.0.1b3.dist-info/RECORD
stairs-0.0.1b3.dist-info/WHEEL
stairs-0.0.1b3.dist-info/top_level.txt
