Metadata-Version: 2.1
Name: stairs
Version: 0.0.1b3
Summary: Context manager for transaction management using SQLAlchemy
Home-page: UNKNOWN
Author: Alexander Sidorov
Author-email: alex.n.sidorov@gmail.com
License: UNKNOWN
Keywords: contextlib db postgresqlsqlalchemy sqlalchemy-core
Platform: UNKNOWN
Classifier: Development Status :: 4 - Beta
Classifier: Environment :: Console
Classifier: Intended Audience :: Developers
Classifier: License :: OSI Approved :: Apache Software License
Classifier: Operating System :: MacOS :: MacOS X
Classifier: Operating System :: POSIX :: Linux
Classifier: Programming Language :: Python :: 3.6
Classifier: Topic :: Database
Classifier: Topic :: Software Development :: Libraries :: Python Modules
Requires-Python: >=3
Requires-Dist: SQLAlchemy (>=1.1)
